vcs/main.py
vcs/commands/add.py
vcs/commands/checkout.py
vcs/commands/cleanup.py
vcs/commands/commit.py
vcs/commands/init.py
vcs/commands/log.py
vcs/commands/show.py
vcs_core-0.1.0.dist-info/METADATA
vcs_core-0.1.0.dist-info/WHEEL
vcs_core-0.1.0.dist-info/entry_points.txt
vcs_core-0.1.0.dist-info/top_level.txt
vcs_core-0.1.0.dist-info/RECORD
