Metadata-Version: 2.4
Name: vcs-core
Version: 0.1.0
Summary: A simple version control system
Author: Arjun
